crinstaniev/__init__.py
crinstaniev/mammals/__init__.py
crinstaniev/mammals/dog.py
crinstaniev-1.0.2.dist-info/LICENSE.txt
crinstaniev-1.0.2.dist-info/METADATA
crinstaniev-1.0.2.dist-info/WHEEL
crinstaniev-1.0.2.dist-info/top_level.txt
crinstaniev-1.0.2.dist-info/RECORD
