Metadata-Version: 2.1
Name: crinstaniev
Version: 1.0.2
Summary: The description of your package
Home-page: UNKNOWN
Author: Your Name
Author-email: example@abc.com
License: MIT
Platform: UNKNOWN
Classifier: License :: OSI Approved :: MIT License
Classifier: Programming Language :: Python :: 3
Classifier: Programming Language :: Python :: 3.7
Requires-Dist: numpy
Requires-Dist: pandas
